cnewtonprop/__init__.py
cnewtonprop/propagator.pyx
cnewtonprop-0.0.1.dev1.dist-info/AUTHORS.rst
cnewtonprop-0.0.1.dev1.dist-info/LICENSE
cnewtonprop-0.0.1.dev1.dist-info/METADATA
cnewtonprop-0.0.1.dev1.dist-info/WHEEL
cnewtonprop-0.0.1.dev1.dist-info/top_level.txt
cnewtonprop-0.0.1.dev1.dist-info/RECORD
