Metadata-Version: 2.1
Name: cnewtonprop
Version: 0.0.1.dev1
Summary: Cython implementation of the Newton propagator for QuTiP Qobjs
Home-page: https://github.com/qucontrol/cnewtonprop
Author: Michael Goerz
Author-email: mail@michaelgoerz.net
License: BSD license
Keywords: cnewtonprop
Platform: UNKNOWN
Classifier: Development Status :: 1 - Planning
Classifier: Intended Audience :: Developers
Classifier: License :: OSI Approved :: BSD License
Classifier: Natural Language :: English
Classifier: Programming Language :: Cython 
Classifier: Programming Language :: Python :: 3.5
Classifier: Programming Language :: Python :: 3.6
Classifier: Programming Language :: Python :: 3.7
Requires-Python: >=3.5
Provides-Extra: dev
Requires-Dist: coverage ; extra == 'dev'
Requires-Dist: pytest ; extra == 'dev'
Requires-Dist: pytest-cov ; extra == 'dev'
Requires-Dist: pytest-xdist ; extra == 'dev'
Requires-Dist: twine ; extra == 'dev'
Requires-Dist: pep8 ; extra == 'dev'
Requires-Dist: flake8 ; extra == 'dev'
Requires-Dist: wheel ; extra == 'dev'
Requires-Dist: sphinx ; extra == 'dev'
Requires-Dist: sphinx-autobuild ; extra == 'dev'
Requires-Dist: sphinx-rtd-theme ; extra == 'dev'
Requires-Dist: sphinx-autodoc-typehints ; extra == 'dev'
Requires-Dist: gitpython ; extra == 'dev'
Requires-Dist: better-apidoc ; extra == 'dev'
Requires-Dist: jupyter ; extra == 'dev'
Requires-Dist: nbval ; extra == 'dev'
Requires-Dist: nbsphinx ; extra == 'dev'
Requires-Dist: watermark ; extra == 'dev'
